pyratelimit/__init__.py
pyratelimit/pyratelimit.py
pyratelimit/pyratelimit_exception.py
pyratelimit/redis_helper.py
pyratelimit-0.1.9.dist-info/LICENSE.txt
pyratelimit-0.1.9.dist-info/METADATA
pyratelimit-0.1.9.dist-info/WHEEL
pyratelimit-0.1.9.dist-info/top_level.txt
pyratelimit-0.1.9.dist-info/RECORD
